{
  "url_num": 1431,
  "name": "Hon. (Ven.) Athuraliye Rathana  Thero, M.P.",
  "image_url": "https://www.parliament.lk/uploads/images/members/profile_images/thumbs/1431.jpg",
  "party": "Our Power of People Party (OPPP)",
  "electoral_district": "National List",
  "date_of_birth": "10-10-1962",
  "civil_status": null,
  "religion": "Buddhism",
  "profession": null,
  "phone": "0112882198",
  "address": "\"Sadaham Sewana\"Gothami Uyana,Obesekarapura,Rajagiriya.",
  "phone_sitting": "0333338950",
  "address_sitting": null,
  "email": "rathana_a@parliament.lk",
  "source_url": "https://www.parliament.lk/en/members-of-parliament/directory-of-members/viewMember/1431"
}