{
  "url_num": 3076,
  "name": "Hon. Patali Champika Ranawaka, M.P.",
  "image_url": "https://www.parliament.lk/uploads/images/members/profile_images/thumbs/3076.jpg",
  "party": "Samagi Jana Balawegaya (SJB)",
  "electoral_district": "Colombo",
  "date_of_birth": "04-08-1965",
  "civil_status": "Divorced",
  "religion": "Buddhism",
  "profession": "Engineer",
  "phone": "0112866125",
  "address": "No. 1/88,Jayanthipura Road,Battaramulla.",
  "phone_sitting": "0112866125",
  "address_sitting": null,
  "email": "ranawaka_p@parliament.lk",
  "source_url": "https://www.parliament.lk/en/members-of-parliament/directory-of-members/viewMember/3076",
  "academic_qualifications": "Electrical and Electronics Engineering",
  "professional_qualifications": "Electrical Engineer",
  "attendance_9th_present": 95,
  "attendance_9th_absent": 64,
  "attendance_8th_present": 109,
  "attendance_8th_absent": 143
}