{
  "url_num": 3254,
  "name": "Hon. Wimalaweera Dissanayake, M.P.",
  "image_url": "https://www.parliament.lk/uploads/images/members/profile_images/thumbs/3254.jpg",
  "party": "Sri Lanka Podujana Peramuna (SLPP)",
  "electoral_district": "Digamadulla",
  "date_of_birth": "30-06-1954",
  "civil_status": "Married",
  "religion": "Buddhism",
  "profession": "Teacher",
  "phone": "0632240248",
  "address": "C -03Hingurana,Ampara.",
  "phone_sitting": "0632222820",
  "address_sitting": "A 06, Parliament Members Housing Complex,Madiwela,Sri Jayawardenepura Kotte.",
  "email": "dissanayaka_w@parliament.lk",
  "source_url": "https://www.parliament.lk/en/members-of-parliament/directory-of-members/viewMember/3254",
  "academic_qualifications": "B.A (Hon) - University of Colombo; M.Sc. (Education) - University Of Peradeniya G.C.E. A/L; G.C.E. O/L",
  "professional_qualifications": null
}