{
  "url_num": 3438,
  "name": "Hon. Yadamini Gunawardena, M.P.",
  "image_url": "https://www.parliament.lk/uploads/images/members/profile_images/thumbs/3438.jpg",
  "party": "Sri Lanka Podujana Peramuna (SLPP)",
  "electoral_district": "National List",
  "date_of_birth": "04-01-1981",
  "civil_status": null,
  "religion": null,
  "profession": null,
  "phone": "0714311163",
  "address": "Boralugoda,Kosgama.",
  "phone_sitting": "0714311163",
  "address_sitting": "No. 84,Kirulapona Avenue,Colombo 05.",
  "email": "yadamini_g@parliament.lk",
  "source_url": "https://www.parliament.lk/en/members-of-parliament/directory-of-members/viewMember/3438"
}